python_extras/__init__.py
python_extras/tools.py
python_extras/types.py
python_extras-0.1.6.dist-info/LICENSE
python_extras-0.1.6.dist-info/METADATA
python_extras-0.1.6.dist-info/WHEEL
python_extras-0.1.6.dist-info/RECORD
